{
  "9346":  "KROGER - JADE DESIGNER FRAGRANCES",
  "12164": "Nordstrom Corporate",
  "12165": "Nordstrom Rack/Hautelook",
  "11092": "Meijer",
  "14893": "Target Corporation",
  "15235": "The Marmaxx Group",
  "15527": "TJX Australia",
  "15528": "TJX UK",
  "16086": "WMI (TJX Canada)",
  "16542": "Scheels",
  "16670": "CVS Health",
  "17133": "Amazon US",
  "1765":  "Amazon Australia",
  "1766":  "Amazon Canada",
  "1770":  "Amazon Japan",
  "42207": "Amazon EU",
  "9149":  "Kohl's, Inc.",
  "3094":  "Boots UK Ltd.",
  "64630": "HEB",
  "15732": "Ulta Inc.",
  "15925": "Walgreens Corporation",
  "15929": "Walmart USA",
  "15930": "Walmart.com",
  "3026":  "Bloomingdales",
  "5869":  "Fred Meyer",
  "6674":  "iHerb",
  "9721":  "Lazy Acres Natural Living",
  "10310": "Lotus Light (Whole Foods)",
  "10966": "Mecca Brands",
  "12222": "Oliver Bonas Ltd.",
  "12270": "Oz Hair & Beauty Pty Ltd",
  "12618": "PrettyLittleThing.com Limited",
  "13634": "Selfridges & Co.",
  "13641": "SEPHORA (SINGAPORE)",
  "13642": "SEPHORA (THAILAND)",
  "13643": "Sephora Malaysia - Beauty in Motion Sdn Bhd",
  "13989": "Shopbop",
  "14747": "Timberwolf Ventures",
  "15413": "Thrive Market",
  "15946": "Well.ca",
  "16619": "The Paradies Shops LLC",
  "16651": "Urban Outfitters",
  "89355": "Ulta Beauty SAPI de CV",
  "326096":"TJX - Sierra",
  "70436": "Marshall Retail Group",
  "48920": "World Market Management Services LLC",
  "69022": "KeHE Distributors, LLC",
  "66403": "Sephora Middle East (ME)",
  "5778":  "Feelunique/Sephora UK",
  "2798":  "Beautylish Inc",
  "268182":"Bealls Inc.",
  "16374": "Grove Collaborative",
  "16448": "Lulus",
  "3286":  "Bristol Farms-CA",
  "7084":  "JC Penney",
  "9461":  "Lakewinds Food Co-op",
  "11503": "Mickey Fine Pharmacy",
  "12068": "NIGEL BEAUTY EMPORIUM",
  "12185": "Number One Beauty",
  "12553": "Planet Beauty - Camarillo",
  "12555": "PLANET BEAUTY - DANA POINT",
  "12563": "PLANET BEAUTY - NEWPORT BEACH",
  "12567": "Planet Beauty - San Clemente",
  "13027": "River Valley (Cavallaro)",
  "14026": "Simons Inc",
  "16238": "AAFES - Store/DC",
  "16284": "Bell's Nursery",
  "16351": "Face & Body Emporium",
  "16363": "Fruitful Yield",
  "16406": "ISLAND NATURALS",
  "16492": "NEXCOM",
  "16515": "Plum Market Aventura",
  "16516": "Plum Market BLM",
  "16518": "Plum Market WBL",
  "16618": "The Paper Store",
  "16960": "San Manuel Casino",
  "16970": "Warner Bros. Studio Ops",
  "43314": "New Leaf Community Markets",
  "43315": "Superette",
  "178992":"Kirei Beauty",
  "184493":"Boxout LLC",
  "307887":"Focus on Beauty Brands (Ko'a Kea)",
  "429478":"NAZ & CO SA",
  "208026":"Focus on Beauty Brands (Harmons)"
}
